ceasylog/Logger.py
ceasylog/LoggerConfiger.py
ceasylog/LoggerLevel.py
ceasylog/LoggerNetworkConfiger.py
ceasylog/LoggerStatic.py
ceasylog/__init__.py
casseroles_sdk-1.2.7.dist-info/LICENSE
casseroles_sdk-1.2.7.dist-info/METADATA
casseroles_sdk-1.2.7.dist-info/WHEEL
casseroles_sdk-1.2.7.dist-info/top_level.txt
casseroles_sdk-1.2.7.dist-info/RECORD
